<?xml version='1.0' encoding='utf-8'?>
<!DOCTYPE hibernate-configuration PUBLIC
    "-//Hibernate/Hibernate Configuration DTD//EN"
    "http://www.hibernate.org/dtd/hibernate-configuration-3.0.dtd">
<hibernate-configuration>
  <session-factory>
    <property name="connection.url">jdbc:mysql://localhost:3306/stock</property>
    <property name="connection.driver_class">com.mysql.jdbc.Driver</property>
    <mapping class="io.github.kingschan1204.istock.model.po.StockMasterEntity"/>
    <!-- DB schema will be updated if needed -->
    <!-- <property name="hbm2ddl.auto">update</property> -->
  </session-factory>
</hibernate-configuration>